src/BpC.v
module BpC(input Gjk, input Pjk, input Gij, input Pij, input ci,
           output Gik, output Pik, output cj);

assign Gik = Gjk | (Gij & Pjk);
assign Pik = Pjk & Pij;
assign cj =Gij | (Pij & ci);

endmodule

src/AC.v
module AC(input xi, input yi, input ci,
        output zi, output Gij, output Pii);

assign Gij = xi & yi;
assign Pii = xi | yi;
assign zi = ci ^ (xi ^ yi);

endmodule

src/adder/CLA4b.v
module CLA4b(input [3:0] x,
            input [3:0] y,
            input c0,
            output [3:0] z,
            output c4);

wire c1, c2, c3;
wire P00, P11, P22, P33;
wire P01, P23, P03;
wire G00, G11, G22, G33;
wire G01, G23, G03;

AC ac0 (.xi(x[0]), .yi(y[0]), .ci(c0), .zi(z[0]), .Gij(G00), .Pii(P00));
AC ac1 (.xi(x[1]), .yi(y[1]), .ci(c1), .zi(z[1]), .Gij(G11), .Pii(P11));
AC ac2 (.xi(x[2]), .yi(y[2]), .ci(c2), .zi(z[2]), .Gij(G22), .Pii(P22));
AC ac3 (.xi(x[3]), .yi(y[3]), .ci(c3), .zi(z[3]), .Gij(G33), .Pii(P33));

BpC bc0 (.Gjk(G11), .Pjk(P11), .Gij(G00), .Pij(P00), .ci(c0), .Gik(G01), .Pik(P01), .cj(c1));
BpC bc1 (.Gjk(G33), .Pjk(P33), .Gij(G22), .Pij(P22), .ci(c2), .Gik(G23), .Pik(P23), .cj(c3));
BpC bc2 (.Gjk(G23), .Pjk(P23), .Gij(G01), .Pij(P01), .ci(c0), .Gik(G03), .Pik(P03), .cj(c2));

assign c4 = G03 | (P03 & c0);

endmodule

tb/CLA4b_tb.v
module CLA4b_tb;

reg [3:0] x;
reg [3:0] y;
reg c0;

wire [3:0]z;
wire c4;

CLA4b uut (.x(x), .y(y), .c0(c0), .z(z), .c4(c4));

   integer i;
   integer j;

initial begin
    $dumpfile("cla4b.vcd");
    $dumpvars(0, CLA4b_tb); 
    c0 = 0;

    for(i = 0; i < 16; i=i+1) begin
        for(j = 0; j < 16; j=j+1) begin
            x = i[3:0];
            y = j[3:0];

            #10;

        end
    end
    $finish;
end
endmodule

sim/cla4b.vcd
$date
	Mon Mar 16 18:22:15 2026
$end
$version
	Icarus Verilog
$end
$timescale
	1s
$end
$scope module CLA4b_tb $end
$var wire 4 ! z [3:0] $end
$var wire 1 " c4 $end
$var reg 1 # c0 $end
$var reg 4 $ x [3:0] $end
$var reg 4 % y [3:0] $end
$var integer 32 & i [31:0] $end
$var integer 32 ' j [31:0] $end
$scope module uut $end
$var wire 1 # c0 $end
$var wire 1 " c4 $end
$var wire 4 ( x [3:0] $end
$var wire 4 ) y [3:0] $end
$var wire 4 * z [3:0] $end
$var wire 1 + c3 $end
$var wire 1 , c2 $end
$var wire 1 - c1 $end
$var wire 1 . P33 $end
$var wire 1 / P23 $end
$var wire 1 0 P22 $end
$var wire 1 1 P11 $end
$var wire 1 2 P03 $end
$var wire 1 3 P01 $end
$var wire 1 4 P00 $end
$var wire 1 5 G33 $end
$var wire 1 6 G23 $end
$var wire 1 7 G22 $end
$var wire 1 8 G11 $end
$var wire 1 9 G03 $end
$var wire 1 : G01 $end
$var wire 1 ; G00 $end
$scope module ac0 $end
$var wire 1 ; Gij $end
$var wire 1 4 Pii $end
$var wire 1 # ci $end
$var wire 1 < xi $end
$var wire 1 = yi $end
$var wire 1 > zi $end
$upscope $end
$scope module ac1 $end
$var wire 1 8 Gij $end
$var wire 1 1 Pii $end
$var wire 1 ? xi $end
$var wire 1 @ yi $end
$var wire 1 A zi $end
$var wire 1 - ci $end
$upscope $end
$scope module ac2 $end
$var wire 1 7 Gij $end
$var wire 1 0 Pii $end
$var wire 1 B xi $end
$var wire 1 C yi $end
$var wire 1 D zi $end
$var wire 1 , ci $end
$upscope $end
$scope module ac3 $end
$var wire 1 5 Gij $end
$var wire 1 . Pii $end
$var wire 1 E xi $end
$var wire 1 F yi $end
$var wire 1 G zi $end
$var wire 1 + ci $end
$upscope $end
$scope module bc0 $end
$var wire 1 ; Gij $end
$var wire 1 : Gik $end
$var wire 1 8 Gjk $end
$var wire 1 4 Pij $end
$var wire 1 3 Pik $end
$var wire 1 1 Pjk $end
$var wire 1 # ci $end
$var wire 1 - cj $end
$upscope $end
$scope module bc1 $end
$var wire 1 7 Gij $end
$var wire 1 6 Gik $end
$var wire 1 5 Gjk $end
$var wire 1 0 Pij $end
$var wire 1 / Pik $end
$var wire 1 . Pjk $end
$var wire 1 + cj $end
$var wire 1 , ci $end
$upscope $end
$scope module bc2 $end
$var wire 1 : Gij $end
$var wire 1 9 Gik $end
$var wire 1 6 Gjk $end
$var wire 1 3 Pij $end
$var wire 1 2 Pik $end
$var wire 1 / Pjk $end
$var wire 1 # ci $end
$var wire 1 , cj $end
$upscope $end
$upscope $end
$upscope $end
$enddefinitions $end
$comment Show the parameter values. $end
$dumpall
$end
#0
$dumpvars
0G
0F
0E
0D
0C
0B
0A
0@
0?
0>
0=
0<
0;
0:
09
08
07
06
05
04
03
02
01
00
0/
0.
0-
0,
0+
b0 *
b0 )
b0 (
b0 '
b0 &
b0 %
b0 $
0#
0"
b0 !
$end
#10
b1 !
b1 *
1>
14
1=
b1 %
b1 )
b1 '
#20
0>
b10 !
b10 *
1A
04
11
0=
1@
b10 %
b10 )
b10 '
#30
13
b11 !
b11 *
1>
14
1=
b11 %
b11 )
b11 '
#40
0>
03
0A
b100 !
b100 *
1D
04
01
10
0=
0@
1C
b100 %
b100 )
b100 '
#50
b101 !
b101 *
1>
14
1=
b101 %
b101 )
b101 '
#60
0>
b110 !
b110 *
1A
04
11
0=
1@
b110 %
b110 )
b110 '
#70
13
b111 !
b111 *
1>
14
1=
b111 %
b111 )
b111 '
#80
0>
03
0A
0D
b1000 !
b1000 *
1G
04
01
00
1.
0=
0@
0C
1F
b1000 %
b1000 )
b1000 '
#90
b1001 !
b1001 *
1>
14
1=
b1001 %
b1001 )
b1001 '
#100
0>
b1010 !
b1010 *
1A
04
11
0=
1@
b1010 %
b1010 )
b1010 '
#110
13
b1011 !
b1011 *
1>
14
1=
b1011 %
b1011 )
b1011 '
#120
0>
03
0A
1/
b1100 !
b1100 *
1D
04
01
10
0=
0@
1C
b1100 %
b1100 )
b1100 '
#130
b1101 !
b1101 *
1>
14
1=
b1101 %
b1101 )
b1101 '
#140
0>
b1110 !
b1110 *
1A
04
11
0=
1@
b1110 %
b1110 )
b1110 '
#150
12
13
b1111 !
b1111 *
1>
14
1=
b1111 %
b1111 )
b1111 '
#160
02
03
0A
0D
0/
b1 !
b1 *
0G
01
00
0.
0=
0@
0C
0F
1<
b0 %
b0 )
b1 $
b1 (
b1 &
b0 '
#170
1A
1-
b10 !
b10 *
0>
1;
1=
b1 %
b1 )
b1 '
#180
0-
1>
13
b11 !
b11 *
1A
0;
11
0=
1@
b10 %
b10 )
b10 '
#190
1D
1,
1:
0A
1-
b100 !
b100 *
0>
1;
1=
b11 %
b11 )
b11 '
#200
0,
0G
0:
0+
0-
1>
03
0A
b101 !
b101 *
1D
0;
01
10
0=
0@
1C
b100 %
b100 )
b100 '
#210
1A
1-
b110 !
b110 *
0>
1;
1=
b101 %
b101 )
b101 '
#220
0-
1>
13
b111 !
b111 *
1A
0;
11
0=
1@
b110 %
b110 )
b110 '
#230
1G
1+
0D
1,
1:
0A
1-
b1000 !
b1000 *
0>
1;
1=
b111 %
b111 )
b111 '
#240
0,
0:
0+
0-
1>
03
0A
0D
b1001 !
b1001 *
1G
0;
01
00
1.
0=
0@
0C
1F
b1000 %
b1000 )
b1000 '
#250
1A
1-
b1010 !
b1010 *
0>
1;
1=
b1001 %
b1001 )
b1001 '
#260
0-
1>
13
b1011 !
b1011 *
1A
0;
11
0=
1@
b1010 %
b1010 )
b1010 '
#270
1D
1,
1:
0A
1-
b1100 !
b1100 *
0>
1;
1=
b1011 %
b1011 )
b1011 '
#280
0"
0,
09
1G
0:
0+
0-
1>
03
0A
1/
b1101 !
b1101 *
1D
0;
01
10
0=
0@
1C
b1100 %
b1100 )
b1100 '
#290
1A
1-
b1110 !
b1110 *
0>
1;
1=
b1101 %
b1101 )
b1101 '
#300
12
0-
1>
13
b1111 !
b1111 *
1A
0;
11
0=
1@
b1110 %
b1110 )
b1110 '
#310
0G
1"
1+
19
0D
1,
1:
0A
1-
b0 !
b0 *
0>
1;
1=
b1111 %
b1111 )
b1111 '
#320
0"
09
0,
0+
0:
1A
02
0D
0/
b10 !
b10 *
0G
0-
03
00
0.
0;
04
0=
0@
0C
0F
0<
1?
b0 %
b0 )
b10 $
b10 (
b10 &
b0 '
#330
13
b11 !
b11 *
1>
14
1=
b1 %
b1 )
b1 '
#340
1D
1,
03
0>
1:
b100 !
b100 *
0A
04
18
0=
1@
b10 %
b10 )
b10 '
#350
13
b101 !
b101 *
1>
14
1=
b11 %
b11 )
b11 '
#360
0G
0,
0+
03
0>
0:
1A
b110 !
b110 *
1D
04
08
10
0=
0@
1C
b100 %
b100 )
b100 '
#370
13
b111 !
b111 *
1>
14
1=
b101 %
b101 )
b101 '
#380
1G
1+
0D
1,
03
0>
1:
b1000 !
b1000 *
0A
04
18
0=
1@
b110 %
b110 )
b110 '
#390
13
b1001 !
b1001 *
1>
14
1=
b111 %
b111 )
b111 '
#400
0,
0+
03
0>
0:
1A
0D
b1010 !
b1010 *
1G
04
08
00
1.
0=
0@
0C
1F
b1000 %
b1000 )
b1000 '
#410
13
b1011 !
b1011 *
1>
14
1=
b1001 %
b1001 )
b1001 '
#420
1D
1,
03
0>
1:
b1100 !
b1100 *
0A
04
18
0=
1@
b1010 %
b1010 )
b1010 '
#430
13
b1101 !
b1101 *
1>
14
1=
b1011 %
b1011 )
b1011 '
#440
1G
0,
0+
03
0>
0:
1A
1/
b1110 !
b1110 *
1D
04
08
10
0=
0@
1C
b1100 %
b1100 )
b1100 '
#450
12
13
b1111 !
b1111 *
1>
14
1=
b1101 %
b1101 )
b1101 '
#460
0G
1"
1+
19
0D
02
1,
03
0>
1:
b0 !
b0 *
0A
04
18
0=
1@
b1110 %
b1110 )
b1110 '
#470
12
13
b1 !
b1 *
1>
14
1=
b1111 %
b1111 )
b1111 '
#480
0"
09
0,
0+
02
0:
1A
0D
0/
b11 !
b11 *
0G
08
00
0.
0=
0@
0C
0F
1<
b0 %
b0 )
b11 $
b11 (
b11 &
b0 '
#490
1D
1,
1:
0A
1-
b100 !
b100 *
0>
1;
1=
b1 %
b1 )
b1 '
#500
0-
1>
b101 !
b101 *
0A
0;
18
0=
1@
b10 %
b10 )
b10 '
#510
1A
1-
b110 !
b110 *
0>
1;
1=
b11 %
b11 )
b11 '
#520
0,
0G
0:
0+
0-
1>
1A
b111 !
b111 *
1D
0;
08
10
0=
0@
1C
b100 %
b100 )
b100 '
#530
1G
1+
0D
1,
1:
0A
1-
b1000 !
b1000 *
0>
1;
1=
b101 %
b101 )
b101 '
#540
0-
1>
b1001 !
b1001 *
0A
0;
18
0=
1@
b110 %
b110 )
b110 '
#550
1A
1-
b1010 !
b1010 *
0>
1;
1=
b111 %
b111 )
b111 '
#560
0,
0:
0+
0-
1>
1A
0D
b1011 !
b1011 *
1G
0;
08
00
1.
0=
0@
0C
1F
b1000 %
b1000 )
b1000 '
#570
1D
1,
1:
0A
1-
b1100 !
b1100 *
0>
1;
1=
b1001 %
b1001 )
b1001 '
#580
0-
1>
b1101 !
b1101 *
0A
0;
18
0=
1@
b1010 %
b1010 )
b1010 '
#590
1A
1-
b1110 !
b1110 *
0>
1;
1=
b1011 %
b1011 )
b1011 '
#600
0"
0,
09
1G
0:
12
0+
0-
1>
1A
1/
b1111 !
b1111 *
1D
0;
08
10
0=
0@
1C
b1100 %
b1100 )
b1100 '
#610
0G
1"
1+
19
0D
1,
1:
0A
1-
b0 !
b0 *
0>
1;
1=
b1101 %
b1101 )
b1101 '
#620
0-
1>
b1 !
b1 *
0A
0;
18
0=
1@
b1110 %
b1110 )
b1110 '
#630
1A
1-
b10 !
b10 *
0>
1;
1=
b1111 %
b1111 )
b1111 '
#640
0"
0+
09
1D
0A
0,
02
0/
b100 !
b100 *
0G
0-
0:
03
0.
0;
04
08
01
0=
0@
0C
0F
0<
0?
1B
b0 %
b0 )
b100 $
b100 (
b100 &
b0 '
#650
b101 !
b101 *
1>
14
1=
b1 %
b1 )
b1 '
#660
0>
b110 !
b110 *
1A
04
11
0=
1@
b10 %
b10 )
b10 '
#670
13
b111 !
b111 *
1>
14
1=
b11 %
b11 )
b11 '
#680
1G
0>
03
0A
1+
b1000 !
b1000 *
0D
04
01
17
0=
0@
1C
b100 %
b100 )
b100 '
#690
b1001 !
b1001 *
1>
14
1=
b101 %
b101 )
b101 '
#700
0>
b1010 !
b1010 *
1A
04
11
0=
1@
b110 %
b110 )
b110 '
#710
13
b1011 !
b1011 *
1>
14
1=
b111 %
b111 )
b111 '
#720
0>
03
0A
0+
1D
1/
b1100 !
b1100 *
1G
04
01
07
1.
0=
0@
0C
1F
b1000 %
b1000 )
b1000 '
#730
b1101 !
b1101 *
1>
14
1=
b1001 %
b1001 )
b1001 '
#740
0>
b1110 !
b1110 *
1A
04
11
0=
1@
b1010 %
b1010 )
b1010 '
#750
12
13
b1111 !
b1111 *
1>
14
1=
b1011 %
b1011 )
b1011 '
#760
1"
19
02
16
0G
0>
03
0A
1+
b0 !
b0 *
0D
04
01
17
0=
0@
1C
b1100 %
b1100 )
b1100 '
#770
b1 !
b1 *
1>
14
1=
b1101 %
b1101 )
b1101 '
#780
0>
b10 !
b10 *
1A
04
11
0=
1@
b1110 %
b1110 )
b1110 '
#790
12
13
b11 !
b11 *
1>
14
1=
b1111 %
b1111 )
b1111 '
#800
0"
09
06
02
03
0A
0+
1D
0/
b101 !
b101 *
0G
01
07
0.
0=
0@
0C
0F
1<
b0 %
b0 )
b101 $
b101 (
b101 &
b0 '
#810
1A
1-
b110 !
b110 *
0>
1;
1=
b1 %
b1 )
b1 '
#820
0-
1>
13
b111 !
b111 *
1A
0;
11
0=
1@
b10 %
b10 )
b10 '
#830
1G
1+
0D
1,
1:
0A
1-
b1000 !
b1000 *
0>
1;
1=
b11 %
b11 )
b11 '
#840
0,
0:
0-
1>
03
0A
b1001 !
b1001 *
0D
0;
01
17
0=
0@
1C
b100 %
b100 )
b100 '
#850
1A
1-
b1010 !
b1010 *
0>
1;
1=
b101 %
b101 )
b101 '
#860
0-
1>
13
b1011 !
b1011 *
1A
0;
11
0=
1@
b110 %
b110 )
b110 '
#870
1D
1,
1:
0A
1-
b1100 !
b1100 *
0>
1;
1=
b111 %
b111 )
b111 '
#880
0+
0"
0,
09
0:
0-
1>
03
0A
1D
1/
b1101 !
b1101 *
1G
0;
01
07
1.
0=
0@
0C
1F
b1000 %
b1000 )
b1000 '
#890
1A
1-
b1110 !
b1110 *
0>
1;
1=
b1001 %
b1001 )
b1001 '
#900
12
0-
1>
13
b1111 !
b1111 *
1A
0;
11
0=
1@
b1010 %
b1010 )
b1010 '
#910
0G
1"
1+
19
0D
1,
1:
0A
1-
b0 !
b0 *
0>
1;
1=
b1011 %
b1011 )
b1011 '
#920
0,
0:
02
16
0-
1>
03
0A
b1 !
b1 *
0D
0;
01
17
0=
0@
1C
b1100 %
b1100 )
b1100 '
#930
1A
1-
b10 !
b10 *
0>
1;
1=
b1101 %
b1101 )
b1101 '
#940
12
0-
1>
13
b11 !
b11 *
1A
0;
11
0=
1@
b1110 %
b1110 )
b1110 '
#950
1D
1,
1:
0A
1-
b100 !
b100 *
0>
1;
1=
b1111 %
b1111 )
b1111 '
#960
0+
0"
09
0,
06
0:
1A
02
1D
0/
b110 !
b110 *
0G
0-
03
07
0.
0;
04
0=
0@
0C
0F
0<
1?
b0 %
b0 )
b110 $
b110 (
b110 &
b0 '
#970
13
b111 !
b111 *
1>
14
1=
b1 %
b1 )
b1 '
#980
1G
1+
0D
1,
03
0>
1:
b1000 !
b1000 *
0A
04
18
0=
1@
b10 %
b10 )
b10 '
#990
13
b1001 !
b1001 *
1>
14
1=
b11 %
b11 )
b11 '
#1000
0,
03
0>
0:
1A
b1010 !
b1010 *
0D
04
08
17
0=
0@
1C
b100 %
b100 )
b100 '
#1010
13
b1011 !
b1011 *
1>
14
1=
b101 %
b101 )
b101 '
#1020
1D
1,
03
0>
1:
b1100 !
b1100 *
0A
04
18
0=
1@
b110 %
b110 )
b110 '
#1030
13
b1101 !
b1101 *
1>
14
1=
b111 %
b111 )
b111 '
#1040
0+
0,
03
0>
0:
1A
1D
1/
b1110 !
b1110 *
1G
04
08
07
1.
0=
0@
0C
1F
b1000 %
b1000 )
b1000 '
#1050
12
13
b1111 !
b1111 *
1>
14
1=
b1001 %
b1001 )
b1001 '
#1060
0G
1"
1+
19
0D
02
1,
03
0>
1:
b0 !
b0 *
0A
04
18
0=
1@
b1010 %
b1010 )
b1010 '
#1070
12
13
b1 !
b1 *
1>
14
1=
b1011 %
b1011 )
b1011 '
#1080
02
0,
16
03
0>
0:
1A
b10 !
b10 *
0D
04
08
17
0=
0@
1C
b1100 %
b1100 )
b1100 '
#1090
12
13
b11 !
b11 *
1>
14
1=
b1101 %
b1101 )
b1101 '
#1100
1D
02
1,
03
0>
1:
b100 !
b100 *
0A
04
18
0=
1@
b1110 %
b1110 )
b1110 '
#1110
12
13
b101 !
b101 *
1>
14
1=
b1111 %
b1111 )
b1111 '
#1120
0+
0"
09
0,
06
02
0:
1A
1D
0/
b111 !
b111 *
0G
08
07
0.
0=
0@
0C
0F
1<
b0 %
b0 )
b111 $
b111 (
b111 &
b0 '
#1130
1G
1+
0D
1,
1:
0A
1-
b1000 !
b1000 *
0>
1;
1=
b1 %
b1 )
b1 '
#1140
0-
1>
b1001 !
b1001 *
0A
0;
18
0=
1@
b10 %
b10 )
b10 '
#1150
1A
1-
b1010 !
b1010 *
0>
1;
1=
b11 %
b11 )
b11 '
#1160
0,
0:
0-
1>
1A
b1011 !
b1011 *
0D
0;
08
17
0=
0@
1C
b100 %
b100 )
b100 '
#1170
1D
1,
1:
0A
1-
b1100 !
b1100 *
0>
1;
1=
b101 %
b101 )
b101 '
#1180
0-
1>
b1101 !
b1101 *
0A
0;
18
0=
1@
b110 %
b110 )
b110 '
#1190
1A
1-
b1110 !
b1110 *
0>
1;
1=
b111 %
b111 )
b111 '
#1200
0+
0"
0,
09
0:
12
0-
1>
1A
1D
1/
b1111 !
b1111 *
1G
0;
08
07
1.
0=
0@
0C
1F
b1000 %
b1000 )
b1000 '
#1210
0G
1"
1+
19
0D
1,
1:
0A
1-
b0 !
b0 *
0>
1;
1=
b1001 %
b1001 )
b1001 '
#1220
0-
1>
b1 !
b1 *
0A
0;
18
0=
1@
b1010 %
b1010 )
b1010 '
#1230
1A
1-
b10 !
b10 *
0>
1;
1=
b1011 %
b1011 )
b1011 '
#1240
0,
0:
16
0-
1>
1A
b11 !
b11 *
0D
0;
08
17
0=
0@
1C
b1100 %
b1100 )
b1100 '
#1250
1D
1,
1:
0A
1-
b100 !
b100 *
0>
1;
1=
b1101 %
b1101 )
b1101 '
#1260
0-
1>
b101 !
b101 *
0A
0;
18
0=
1@
b1110 %
b1110 )
b1110 '
#1270
1A
1-
b110 !
b110 *
0>
1;
1=
b1111 %
b1111 )
b1111 '
#1280
0"
0D
09
0A
0,
06
b1000 !
b1000 *
1G
02
0-
0:
03
0+
0/
0;
04
08
01
07
00
0=
0@
0C
0F
0<
0?
0B
1E
b0 %
b0 )
b1000 $
b1000 (
b1000 &
b0 '
#1290
b1001 !
b1001 *
1>
14
1=
b1 %
b1 )
b1 '
#1300
0>
b1010 !
b1010 *
1A
04
11
0=
1@
b10 %
b10 )
b10 '
#1310
13
b1011 !
b1011 *
1>
14
1=
b11 %
b11 )
b11 '
#1320
0>
03
0A
1/
b1100 !
b1100 *
1D
04
01
10
0=
0@
1C
b100 %
b100 )
b100 '
#1330
b1101 !
b1101 *
1>
14
1=
b101 %
b101 )
b101 '
#1340
0>
b1110 !
b1110 *
1A
04
11
0=
1@
b110 %
b110 )
b110 '
#1350
12
13
b1111 !
b1111 *
1>
14
1=
b111 %
b111 )
b111 '
#1360
1"
02
19
0>
03
0A
0/
0D
16
b0 !
b0 *
0G
04
01
00
15
0=
0@
0C
1F
b1000 %
b1000 )
b1000 '
#1370
b1 !
b1 *
1>
14
1=
b1001 %
b1001 )
b1001 '
#1380
0>
b10 !
b10 *
1A
04
11
0=
1@
b1010 %
b1010 )
b1010 '
#1390
13
b11 !
b11 *
1>
14
1=
b1011 %
b1011 )
b1011 '
#1400
0>
03
0A
1/
b100 !
b100 *
1D
04
01
10
0=
0@
1C
b1100 %
b1100 )
b1100 '
#1410
b101 !
b101 *
1>
14
1=
b1101 %
b1101 )
b1101 '
#1420
0>
b110 !
b110 *
1A
04
11
0=
1@
b1110 %
b1110 )
b1110 '
#1430
12
13
b111 !
b111 *
1>
14
1=
b1111 %
b1111 )
b1111 '
#1440
0"
02
09
03
0A
0/
0D
06
b1001 !
b1001 *
1G
01
00
05
0=
0@
0C
0F
1<
b0 %
b0 )
b1001 $
b1001 (
b1001 &
b0 '
#1450
1A
1-
b1010 !
b1010 *
0>
1;
1=
b1 %
b1 )
b1 '
#1460
0-
1>
13
b1011 !
b1011 *
1A
0;
11
0=
1@
b10 %
b10 )
b10 '
#1470
1D
1,
1:
0A
1-
b1100 !
b1100 *
0>
1;
1=
b11 %
b11 )
b11 '
#1480
0"
0,
09
1G
0:
0+
0-
1>
03
0A
1/
b1101 !
b1101 *
1D
0;
01
10
0=
0@
1C
b100 %
b100 )
b100 '
#1490
1A
1-
b1110 !
b1110 *
0>
1;
1=
b101 %
b101 )
b101 '
#1500
12
0-
1>
13
b1111 !
b1111 *
1A
0;
11
0=
1@
b110 %
b110 )
b110 '
#1510
0G
1"
1+
19
0D
1,
1:
0A
1-
b0 !
b0 *
0>
1;
1=
b111 %
b111 )
b111 '
#1520
0,
0:
02
0+
0-
1>
03
0A
0/
0D
16
b1 !
b1 *
0G
0;
01
00
15
0=
0@
0C
1F
b1000 %
b1000 )
b1000 '
#1530
1A
1-
b10 !
b10 *
0>
1;
1=
b1001 %
b1001 )
b1001 '
#1540
0-
1>
13
b11 !
b11 *
1A
0;
11
0=
1@
b1010 %
b1010 )
b1010 '
#1550
1D
1,
1:
0A
1-
b100 !
b100 *
0>
1;
1=
b1011 %
b1011 )
b1011 '
#1560
0,
0G
0:
0+
0-
1>
03
0A
1/
b101 !
b101 *
1D
0;
01
10
0=
0@
1C
b1100 %
b1100 )
b1100 '
#1570
1A
1-
b110 !
b110 *
0>
1;
1=
b1101 %
b1101 )
b1101 '
#1580
12
0-
1>
13
b111 !
b111 *
1A
0;
11
0=
1@
b1110 %
b1110 )
b1110 '
#1590
1G
1+
0D
1,
1:
0A
1-
b1000 !
b1000 *
0>
1;
1=
b1111 %
b1111 )
b1111 '
#1600
0"
09
0,
0+
0:
1A
02
0/
0D
06
b1010 !
b1010 *
1G
0-
03
00
05
0;
04
0=
0@
0C
0F
0<
1?
b0 %
b0 )
b1010 $
b1010 (
b1010 &
b0 '
#1610
13
b1011 !
b1011 *
1>
14
1=
b1 %
b1 )
b1 '
#1620
1D
1,
03
0>
1:
b1100 !
b1100 *
0A
04
18
0=
1@
b10 %
b10 )
b10 '
#1630
13
b1101 !
b1101 *
1>
14
1=
b11 %
b11 )
b11 '
#1640
1G
0,
0+
03
0>
0:
1A
1/
b1110 !
b1110 *
1D
04
08
10
0=
0@
1C
b100 %
b100 )
b100 '
#1650
12
13
b1111 !
b1111 *
1>
14
1=
b101 %
b101 )
b101 '
#1660
0G
1"
1+
19
0D
02
1,
03
0>
1:
b0 !
b0 *
0A
04
18
0=
1@
b110 %
b110 )
b110 '
#1670
12
13
b1 !
b1 *
1>
14
1=
b111 %
b111 )
b111 '
#1680
0,
02
0+
03
0>
0:
1A
0/
0D
16
b10 !
b10 *
0G
04
08
00
15
0=
0@
0C
1F
b1000 %
b1000 )
b1000 '
#1690
13
b11 !
b11 *
1>
14
1=
b1001 %
b1001 )
b1001 '
#1700
1D
1,
03
0>
1:
b100 !
b100 *
0A
04
18
0=
1@
b1010 %
b1010 )
b1010 '
#1710
13
b101 !
b101 *
1>
14
1=
b1011 %
b1011 )
b1011 '
#1720
0G
0,
0+
03
0>
0:
1A
1/
b110 !
b110 *
1D
04
08
10
0=
0@
1C
b1100 %
b1100 )
b1100 '
#1730
12
13
b111 !
b111 *
1>
14
1=
b1101 %
b1101 )
b1101 '
#1740
1G
1+
0D
02
1,
03
0>
1:
b1000 !
b1000 *
0A
04
18
0=
1@
b1110 %
b1110 )
b1110 '
#1750
12
13
b1001 !
b1001 *
1>
14
1=
b1111 %
b1111 )
b1111 '
#1760
0"
09
0,
02
0+
0:
1A
0/
0D
06
b1011 !
b1011 *
1G
08
00
05
0=
0@
0C
0F
1<
b0 %
b0 )
b1011 $
b1011 (
b1011 &
b0 '
#1770
1D
1,
1:
0A
1-
b1100 !
b1100 *
0>
1;
1=
b1 %
b1 )
b1 '
#1780
0-
1>
b1101 !
b1101 *
0A
0;
18
0=
1@
b10 %
b10 )
b10 '
#1790
1A
1-
b1110 !
b1110 *
0>
1;
1=
b11 %
b11 )
b11 '
#1800
0"
0,
09
1G
0:
12
0+
0-
1>
1A
1/
b1111 !
b1111 *
1D
0;
08
10
0=
0@
1C
b100 %
b100 )
b100 '
#1810
0G
1"
1+
19
0D
1,
1:
0A
1-
b0 !
b0 *
0>
1;
1=
b101 %
b101 )
b101 '
#1820
0-
1>
b1 !
b1 *
0A
0;
18
0=
1@
b110 %
b110 )
b110 '
#1830
1A
1-
b10 !
b10 *
0>
1;
1=
b111 %
b111 )
b111 '
#1840
0,
0:
02
0+
0-
1>
1A
0/
0D
16
b11 !
b11 *
0G
0;
08
00
15
0=
0@
0C
1F
b1000 %
b1000 )
b1000 '
#1850
1D
1,
1:
0A
1-
b100 !
b100 *
0>
1;
1=
b1001 %
b1001 )
b1001 '
#1860
0-
1>
b101 !
b101 *
0A
0;
18
0=
1@
b1010 %
b1010 )
b1010 '
#1870
1A
1-
b110 !
b110 *
0>
1;
1=
b1011 %
b1011 )
b1011 '
#1880
0,
0G
0:
12
0+
0-
1>
1A
1/
b111 !
b111 *
1D
0;
08
10
0=
0@
1C
b1100 %
b1100 )
b1100 '
#1890
1G
1+
0D
1,
1:
0A
1-
b1000 !
b1000 *
0>
1;
1=
b1101 %
b1101 )
b1101 '
#1900
0-
1>
b1001 !
b1001 *
0A
0;
18
0=
1@
b1110 %
b1110 )
b1110 '
#1910
1A
1-
b1010 !
b1010 *
0>
1;
1=
b1111 %
b1111 )
b1111 '
#1920
0+
0"
1D
09
0A
0,
02
06
b1100 !
b1100 *
1G
0-
0:
03
05
0;
04
08
01
0=
0@
0C
0F
0<
0?
1B
b0 %
b0 )
b1100 $
b1100 (
b1100 &
b0 '
#1930
b1101 !
b1101 *
1>
14
1=
b1 %
b1 )
b1 '
#1940
0>
b1110 !
b1110 *
1A
04
11
0=
1@
b10 %
b10 )
b10 '
#1950
12
13
b1111 !
b1111 *
1>
14
1=
b11 %
b11 )
b11 '
#1960
1"
19
02
16
0G
0>
03
0A
1+
b0 !
b0 *
0D
04
01
17
0=
0@
1C
b100 %
b100 )
b100 '
#1970
b1 !
b1 *
1>
14
1=
b101 %
b101 )
b101 '
#1980
0>
b10 !
b10 *
1A
04
11
0=
1@
b110 %
b110 )
b110 '
#1990
12
13
b11 !
b11 *
1>
14
1=
b111 %
b111 )
b111 '
#2000
02
0>
03
0A
0+
1D
b100 !
b100 *
0G
04
01
07
15
0=
0@
0C
1F
b1000 %
b1000 )
b1000 '
#2010
b101 !
b101 *
1>
14
1=
b1001 %
b1001 )
b1001 '
#2020
0>
b110 !
b110 *
1A
04
11
0=
1@
b1010 %
b1010 )
b1010 '
#2030
12
13
b111 !
b111 *
1>
14
1=
b1011 %
b1011 )
b1011 '
#2040
02
1G
0>
03
0A
1+
b1000 !
b1000 *
0D
04
01
17
0=
0@
1C
b1100 %
b1100 )
b1100 '
#2050
b1001 !
b1001 *
1>
14
1=
b1101 %
b1101 )
b1101 '
#2060
0>
b1010 !
b1010 *
1A
04
11
0=
1@
b1110 %
b1110 )
b1110 '
#2070
12
13
b1011 !
b1011 *
1>
14
1=
b1111 %
b1111 )
b1111 '
#2080
0"
09
02
06
03
0A
0+
1D
b1101 !
b1101 *
1G
01
07
05
0=
0@
0C
0F
1<
b0 %
b0 )
b1101 $
b1101 (
b1101 &
b0 '
#2090
1A
1-
b1110 !
b1110 *
0>
1;
1=
b1 %
b1 )
b1 '
#2100
12
0-
1>
13
b1111 !
b1111 *
1A
0;
11
0=
1@
b10 %
b10 )
b10 '
#2110
0G
1"
1+
19
0D
1,
1:
0A
1-
b0 !
b0 *
0>
1;
1=
b11 %
b11 )
b11 '
#2120
0,
0:
02
16
0-
1>
03
0A
b1 !
b1 *
0D
0;
01
17
0=
0@
1C
b100 %
b100 )
b100 '
#2130
1A
1-
b10 !
b10 *
0>
1;
1=
b101 %
b101 )
b101 '
#2140
12
0-
1>
13
b11 !
b11 *
1A
0;
11
0=
1@
b110 %
b110 )
b110 '
#2150
1D
1,
1:
0A
1-
b100 !
b100 *
0>
1;
1=
b111 %
b111 )
b111 '
#2160
0+
0,
0:
02
0-
1>
03
0A
1D
b101 !
b101 *
0G
0;
01
07
15
0=
0@
0C
1F
b1000 %
b1000 )
b1000 '
#2170
1A
1-
b110 !
b110 *
0>
1;
1=
b1001 %
b1001 )
b1001 '
#2180
12
0-
1>
13
b111 !
b111 *
1A
0;
11
0=
1@
b1010 %
b1010 )
b1010 '
#2190
1G
1+
0D
1,
1:
0A
1-
b1000 !
b1000 *
0>
1;
1=
b1011 %
b1011 )
b1011 '
